[
    {
        "id": 64054,
        "title": "Cameo Cutting",
        "authors": [
            {
                "name": "Marsh, John B.",
                "birth_year": 1835,
                "death_year": 1910
            }
        ],
        "translators": [],
        "subjects": [
            "Cameos",
            "Carving (Decorative arts) -- Technique",
            "Shell engraving -- Handbooks, manuals, etc."
        ],
        "bookshelves": [],
        "languages": [
            "en"
        ],
        "copyright": false,
        "media_type": "Text",
        "formats": {
            "application/x-mobipocket-ebook": "https://www.gutenberg.org/ebooks/64054.kf8.images",
            "application/epub+zip": "https://www.gutenberg.org/ebooks/64054.epub3.images",
            "image/jpeg": "https://www.gutenberg.org/cache/epub/64054/pg64054.cover.medium.jpg",
            "text/plain; charset=utf-8": "https://www.gutenberg.org/files/64054/64054-0.txt",
            "text/html; charset=utf-8": "https://www.gutenberg.org/files/64054/64054-h/64054-h.htm",
            "text/html": "https://www.gutenberg.org/ebooks/64054.html.images",
            "application/rdf+xml": "https://www.gutenberg.org/ebooks/64054.rdf"
        },
        "download_count": 60
    },
    {
        "id": 64085,
        "title": "Mathematische Geographie f\u00fcr Lehrerbildungsanstalten",
        "authors": [
            {
                "name": "Eggert, Erwin",
                "birth_year": null,
                "death_year": null
            }
        ],
        "translators": [],
        "subjects": [
            "Astronomy",
            "Earth (Planet)",
            "Moon",
            "Solar system",
            "Sun"
        ],
        "bookshelves": [],
        "languages": [
            "de"
        ],
        "copyright": false,
        "media_type": "Text",
        "formats": {
            "application/x-mobipocket-ebook": "https://www.gutenberg.org/ebooks/64085.kf8.images",
            "application/epub+zip": "https://www.gutenberg.org/ebooks/64085.epub3.images",
            "text/html": "https://www.gutenberg.org/ebooks/64085.html.images",
            "image/jpeg": "https://www.gutenberg.org/cache/epub/64085/pg64085.cover.medium.jpg",
            "text/plain; charset=utf-8": "https://www.gutenberg.org/files/64085/64085-0.txt",
            "application/rdf+xml": "https://www.gutenberg.org/ebooks/64085.rdf"
        },
        "download_count": 60
    },
    {
        "id": 64232,
        "title": "Le Mar\u00e9chal de Richelieu (1696-1788): d'apr\u00e8s les m\u00e9moires contemporains et des documents in\u00e9dits",
        "authors": [
            {
                "name": "Estr\u00e9e, Paul d'",
                "birth_year": 1838,
                "death_year": 1922
            }
        ],
        "translators": [],
        "subjects": [
            "Diplomats -- France -- Biography",
            "France -- Court and courtiers -- Biography",
            "France -- Foreign relations -- 1715-1774",
            "France -- History -- Louis XV, 1715-1774",
            "Marshals -- France -- Biography",
            "Nobility -- France -- Biography",
            "Richelieu, Louis Fran\u00e7ois Armand du Plessis, duc de, 1696-1788"
        ],
        "bookshelves": [],
        "languages": [
            "fr"
        ],
        "copyright": false,
        "media_type": "Text",
        "formats": {
            "application/x-mobipocket-ebook": "https://www.gutenberg.org/ebooks/64232.kf8.images",
            "application/epub+zip": "https://www.gutenberg.org/ebooks/64232.epub3.images",
            "text/html; charset=utf-8": "https://www.gutenberg.org/files/64232/64232-h/64232-h.htm",
            "image/jpeg": "https://www.gutenberg.org/cache/epub/64232/pg64232.cover.medium.jpg",
            "text/plain; charset=utf-8": "https://www.gutenberg.org/files/64232/64232-0.txt",
            "text/html": "https://www.gutenberg.org/ebooks/64232.html.images",
            "application/rdf+xml": "https://www.gutenberg.org/ebooks/64232.rdf"
        },
        "download_count": 60
    },
    {
        "id": 64967,
        "title": "Clara Barton: A Centenary Tribute to the World's Greatest Humanitarian: Founder of the American Red Cross Society, Author of the American Amendment to the International Red Cross Convention of Geneva, Founder of the National First Aid Association of America",
        "authors": [
            {
                "name": "Young, Charles Sumner",
                "birth_year": null,
                "death_year": null
            }
        ],
        "translators": [],
        "subjects": [
            "Barton, Clara, 1821-1912"
        ],
        "bookshelves": [],
        "languages": [
            "en"
        ],
        "copyright": false,
        "media_type": "Text",
        "formats": {
            "application/x-mobipocket-ebook": "https://www.gutenberg.org/ebooks/64967.kf8.images",
            "application/epub+zip": "https://www.gutenberg.org/ebooks/64967.epub3.images",
            "text/html": "https://www.gutenberg.org/ebooks/64967.html.images",
            "image/jpeg": "https://www.gutenberg.org/cache/epub/64967/pg64967.cover.medium.jpg",
            "text/plain; charset=utf-8": "https://www.gutenberg.org/files/64967/64967-0.txt",
            "application/rdf+xml": "https://www.gutenberg.org/ebooks/64967.rdf"
        },
        "download_count": 60
    },
    {
        "id": 65049,
        "title": "The Evolution Theory, Vol. 2 of 2",
        "authors": [
            {
                "name": "Weismann, August",
                "birth_year": 1834,
                "death_year": 1914
            }
        ],
        "translators": [
            {
                "name": "Thomson, J. Arthur (John Arthur)",
                "birth_year": 1861,
                "death_year": 1933
            },
            {
                "name": "Thomson, Margaret R.",
                "birth_year": null,
                "death_year": null
            }
        ],
        "subjects": [
            "Evolution (Biology)"
        ],
        "bookshelves": [],
        "languages": [
            "en"
        ],
        "copyright": false,
        "media_type": "Text",
        "formats": {
            "application/x-mobipocket-ebook": "https://www.gutenberg.org/ebooks/65049.kf8.images",
            "application/epub+zip": "https://www.gutenberg.org/ebooks/65049.epub3.images",
            "text/html; charset=utf-8": "https://www.gutenberg.org/files/65049/65049-h/65049-h.htm",
            "image/jpeg": "https://www.gutenberg.org/cache/epub/65049/pg65049.cover.medium.jpg",
            "text/plain; charset=utf-8": "https://www.gutenberg.org/files/65049/65049-0.txt",
            "text/html": "https://www.gutenberg.org/ebooks/65049.html.images",
            "application/rdf+xml": "https://www.gutenberg.org/ebooks/65049.rdf"
        },
        "download_count": 60
    },
    {
        "id": 65058,
        "title": "Old Greek Education",
        "authors": [
            {
                "name": "Mahaffy, J. P. (John Pentland)",
                "birth_year": 1839,
                "death_year": 1919
            }
        ],
        "translators": [],
        "subjects": [
            "Education, Greek"
        ],
        "bookshelves": [],
        "languages": [
            "en"
        ],
        "copyright": false,
        "media_type": "Text",
        "formats": {
            "application/x-mobipocket-ebook": "https://www.gutenberg.org/ebooks/65058.kf8.images",
            "application/epub+zip": "https://www.gutenberg.org/ebooks/65058.epub3.images",
            "text/html": "https://www.gutenberg.org/ebooks/65058.html.images",
            "image/jpeg": "https://www.gutenberg.org/cache/epub/65058/pg65058.cover.medium.jpg",
            "text/plain; charset=utf-8": "https://www.gutenberg.org/files/65058/65058-0.txt",
            "application/rdf+xml": "https://www.gutenberg.org/ebooks/65058.rdf"
        },
        "download_count": 60
    },
    {
        "id": 65152,
        "title": "Practical School Discipline: Applied Methods, Part 1",
        "authors": [
            {
                "name": "Beery, Ray Coppock",
                "birth_year": 1892,
                "death_year": null
            }
        ],
        "translators": [],
        "subjects": [
            "School discipline",
            "Teachers"
        ],
        "bookshelves": [],
        "languages": [
            "en"
        ],
        "copyright": false,
        "media_type": "Text",
        "formats": {
            "application/x-mobipocket-ebook": "https://www.gutenberg.org/ebooks/65152.kf8.images",
            "application/epub+zip": "https://www.gutenberg.org/ebooks/65152.epub3.images",
            "image/jpeg": "https://www.gutenberg.org/cache/epub/65152/pg65152.cover.medium.jpg",
            "text/plain; charset=utf-8": "https://www.gutenberg.org/files/65152/65152-0.txt",
            "text/html; charset=utf-8": "https://www.gutenberg.org/files/65152/65152-h/65152-h.htm",
            "text/html": "https://www.gutenberg.org/ebooks/65152.html.images",
            "application/rdf+xml": "https://www.gutenberg.org/ebooks/65152.rdf"
        },
        "download_count": 60
    },
    {
        "id": 65196,
        "title": "Floral Illustrations of the Seasons: Consisting of the Most Beautiful, Hardy and Rare Herbaceous Plants, Cultivated in the Flower Garden",
        "authors": [
            {
                "name": "Roscoe, Margaret",
                "birth_year": null,
                "death_year": 1840
            }
        ],
        "translators": [],
        "subjects": [
            "Floriculture",
            "Flowers -- Pictorial works"
        ],
        "bookshelves": [],
        "languages": [
            "en"
        ],
        "copyright": false,
        "media_type": "Text",
        "formats": {
            "application/x-mobipocket-ebook": "https://www.gutenberg.org/ebooks/65196.kf8.images",
            "application/epub+zip": "https://www.gutenberg.org/ebooks/65196.epub3.images",
            "text/plain; charset=utf-8": "https://www.gutenberg.org/files/65196/65196-0.txt",
            "image/jpeg": "https://www.gutenberg.org/cache/epub/65196/pg65196.cover.medium.jpg",
            "text/html; charset=utf-8": "https://www.gutenberg.org/files/65196/65196-h/65196-h.htm",
            "text/html": "https://www.gutenberg.org/ebooks/65196.html.images",
            "application/rdf+xml": "https://www.gutenberg.org/ebooks/65196.rdf"
        },
        "download_count": 60
    },
    {
        "id": 65228,
        "title": "Eminent literary and scientific men of Italy, Spain, and Portugal. Vol. 3 (of 3)",
        "authors": [
            {
                "name": "Shelley, Mary Wollstonecraft",
                "birth_year": 1797,
                "death_year": 1851
            },
            {
                "name": "Montgomery, James",
                "birth_year": null,
                "death_year": null
            }
        ],
        "translators": [],
        "subjects": [
            "Authors -- Biography",
            "Scientists -- Biography"
        ],
        "bookshelves": [],
        "languages": [
            "en"
        ],
        "copyright": false,
        "media_type": "Text",
        "formats": {
            "application/x-mobipocket-ebook": "https://www.gutenberg.org/ebooks/65228.kf8.images",
            "application/epub+zip": "https://www.gutenberg.org/ebooks/65228.epub3.images",
            "image/jpeg": "https://www.gutenberg.org/cache/epub/65228/pg65228.cover.medium.jpg",
            "text/html; charset=utf-8": "https://www.gutenberg.org/files/65228/65228-h/65228-h.htm",
            "text/plain; charset=utf-8": "https://www.gutenberg.org/files/65228/65228-0.txt",
            "text/html": "https://www.gutenberg.org/ebooks/65228.html.images",
            "application/rdf+xml": "https://www.gutenberg.org/ebooks/65228.rdf"
        },
        "download_count": 60
    },
    {
        "id": 65369,
        "title": "The War History of the 1st/4th Battalion, the Loyal North Lancashire Regiment: now the Loyal Regiment (North Lancashire), 1914-1918",
        "authors": [
            {
                "name": "Anonymous",
                "birth_year": null,
                "death_year": null
            }
        ],
        "translators": [],
        "subjects": [
            "Great Britain. Army. Infantry. Loyal (North Lancashire) Regiment, 1st/4th Battalion",
            "World War, 1914-1918 -- Regimental histories -- Great Britain"
        ],
        "bookshelves": [],
        "languages": [
            "en"
        ],
        "copyright": false,
        "media_type": "Text",
        "formats": {
            "application/x-mobipocket-ebook": "https://www.gutenberg.org/ebooks/65369.kf8.images",
            "application/epub+zip": "https://www.gutenberg.org/ebooks/65369.epub3.images",
            "text/plain; charset=utf-8": "https://www.gutenberg.org/files/65369/65369-0.txt",
            "image/jpeg": "https://www.gutenberg.org/cache/epub/65369/pg65369.cover.medium.jpg",
            "text/html; charset=utf-8": "https://www.gutenberg.org/files/65369/65369-h/65369-h.htm",
            "text/html": "https://www.gutenberg.org/ebooks/65369.html.images",
            "application/rdf+xml": "https://www.gutenberg.org/ebooks/65369.rdf"
        },
        "download_count": 60
    },
    {
        "id": 65414,
        "title": "Travels into Turkey: Containing the most accurate account of the Turks, and neighbouring nations, their manners, customs, religion, superstition, policy, riches, coins, &c.",
        "authors": [
            {
                "name": "Busbecq, Ogier Ghislain de",
                "birth_year": 1522,
                "death_year": 1592
            }
        ],
        "translators": [],
        "subjects": [
            "Turkey -- Description and travel -- Early works to 1800"
        ],
        "bookshelves": [],
        "languages": [
            "en"
        ],
        "copyright": false,
        "media_type": "Text",
        "formats": {
            "application/x-mobipocket-ebook": "https://www.gutenberg.org/ebooks/65414.kf8.images",
            "application/epub+zip": "https://www.gutenberg.org/ebooks/65414.epub3.images",
            "image/jpeg": "https://www.gutenberg.org/cache/epub/65414/pg65414.cover.medium.jpg",
            "text/plain; charset=utf-8": "https://www.gutenberg.org/files/65414/65414-0.txt",
            "text/html; charset=utf-8": "https://www.gutenberg.org/files/65414/65414-h/65414-h.htm",
            "text/html": "https://www.gutenberg.org/ebooks/65414.html.images",
            "application/rdf+xml": "https://www.gutenberg.org/ebooks/65414.rdf"
        },
        "download_count": 60
    },
    {
        "id": 65451,
        "title": "Kill Me if You Can!",
        "authors": [
            {
                "name": "Garrett, Randall",
                "birth_year": 1927,
                "death_year": 1987
            }
        ],
        "translators": [],
        "subjects": [
            "Adventure stories",
            "Dictatorship -- Fiction",
            "Science fiction",
            "Short stories"
        ],
        "bookshelves": [],
        "languages": [
            "en"
        ],
        "copyright": false,
        "media_type": "Text",
        "formats": {
            "application/x-mobipocket-ebook": "https://www.gutenberg.org/ebooks/65451.kf8.images",
            "application/epub+zip": "https://www.gutenberg.org/ebooks/65451.epub3.images",
            "image/jpeg": "https://www.gutenberg.org/cache/epub/65451/pg65451.cover.medium.jpg",
            "text/html; charset=utf-8": "https://www.gutenberg.org/files/65451/65451-h/65451-h.htm",
            "text/plain; charset=utf-8": "https://www.gutenberg.org/files/65451/65451-0.txt",
            "text/html": "https://www.gutenberg.org/ebooks/65451.html.images",
            "application/rdf+xml": "https://www.gutenberg.org/ebooks/65451.rdf"
        },
        "download_count": 60
    },
    {
        "id": 65937,
        "title": "Que nada se sabe",
        "authors": [
            {
                "name": "S\u00e1nchez, Francisco",
                "birth_year": null,
                "death_year": null
            }
        ],
        "translators": [],
        "subjects": [
            "Skepticism -- Early works to 1800"
        ],
        "bookshelves": [],
        "languages": [
            "es"
        ],
        "copyright": false,
        "media_type": "Text",
        "formats": {
            "application/x-mobipocket-ebook": "https://www.gutenberg.org/ebooks/65937.kf8.images",
            "application/epub+zip": "https://www.gutenberg.org/ebooks/65937.epub3.images",
            "text/plain; charset=utf-8": "https://www.gutenberg.org/files/65937/65937-0.txt",
            "text/html; charset=utf-8": "https://www.gutenberg.org/files/65937/65937-h/65937-h.htm",
            "image/jpeg": "https://www.gutenberg.org/cache/epub/65937/pg65937.cover.medium.jpg",
            "text/html": "https://www.gutenberg.org/ebooks/65937.html.images",
            "application/rdf+xml": "https://www.gutenberg.org/ebooks/65937.rdf"
        },
        "download_count": 60
    },
    {
        "id": 65952,
        "title": "Writing Class",
        "authors": [
            {
                "name": "Sheckley, Robert",
                "birth_year": 1928,
                "death_year": 2005
            }
        ],
        "translators": [],
        "subjects": [
            "Authorship -- Fiction",
            "Science fiction",
            "Short stories"
        ],
        "bookshelves": [],
        "languages": [
            "en"
        ],
        "copyright": false,
        "media_type": "Text",
        "formats": {
            "application/x-mobipocket-ebook": "https://www.gutenberg.org/ebooks/65952.kf8.images",
            "application/epub+zip": "https://www.gutenberg.org/ebooks/65952.epub3.images",
            "text/html; charset=utf-8": "https://www.gutenberg.org/files/65952/65952-h/65952-h.htm",
            "image/jpeg": "https://www.gutenberg.org/cache/epub/65952/pg65952.cover.medium.jpg",
            "text/plain; charset=utf-8": "https://www.gutenberg.org/files/65952/65952-0.txt",
            "text/html": "https://www.gutenberg.org/ebooks/65952.html.images",
            "application/rdf+xml": "https://www.gutenberg.org/ebooks/65952.rdf"
        },
        "download_count": 60
    },
    {
        "id": 66109,
        "title": "Young Engineer's Guide",
        "authors": [
            {
                "name": "Rohan, J. V.",
                "birth_year": null,
                "death_year": null
            }
        ],
        "translators": [],
        "subjects": [
            "Steam engineering"
        ],
        "bookshelves": [],
        "languages": [
            "en"
        ],
        "copyright": false,
        "media_type": "Text",
        "formats": {
            "application/x-mobipocket-ebook": "https://www.gutenberg.org/ebooks/66109.kf8.images",
            "application/epub+zip": "https://www.gutenberg.org/ebooks/66109.epub3.images",
            "image/jpeg": "https://www.gutenberg.org/cache/epub/66109/pg66109.cover.medium.jpg",
            "text/html; charset=utf-8": "https://www.gutenberg.org/files/66109/66109-h/66109-h.htm",
            "text/plain; charset=utf-8": "https://www.gutenberg.org/files/66109/66109-0.txt",
            "text/html": "https://www.gutenberg.org/ebooks/66109.html.images",
            "application/rdf+xml": "https://www.gutenberg.org/ebooks/66109.rdf"
        },
        "download_count": 60
    },
    {
        "id": 66442,
        "title": "The Minor Horrors of War",
        "authors": [
            {
                "name": "Shipley, A. E. (Arthur Everett), Sir",
                "birth_year": 1861,
                "death_year": 1927
            }
        ],
        "translators": [],
        "subjects": [
            "Insect pests",
            "Insects as carriers of disease",
            "Leeches",
            "Military hygiene",
            "Mites",
            "Ticks",
            "World War, 1914-1918 -- Health aspects"
        ],
        "bookshelves": [],
        "languages": [
            "en"
        ],
        "copyright": false,
        "media_type": "Text",
        "formats": {
            "application/x-mobipocket-ebook": "https://www.gutenberg.org/ebooks/66442.kf8.images",
            "application/epub+zip": "https://www.gutenberg.org/ebooks/66442.epub3.images",
            "text/html": "https://www.gutenberg.org/ebooks/66442.html.images",
            "application/octet-stream": "https://www.gutenberg.org/files/66442/66442-0.zip",
            "image/jpeg": "https://www.gutenberg.org/cache/epub/66442/pg66442.cover.medium.jpg",
            "text/plain": "https://www.gutenberg.org/ebooks/66442.txt.utf-8",
            "application/rdf+xml": "https://www.gutenberg.org/ebooks/66442.rdf",
            "text/plain; charset=us-ascii": "https://www.gutenberg.org/files/66442/66442-0.txt"
        },
        "download_count": 60
    },
    {
        "id": 66650,
        "title": "The Life of the Grasshopper",
        "authors": [
            {
                "name": "Fabre, Jean-Henri",
                "birth_year": 1823,
                "death_year": 1915
            }
        ],
        "translators": [
            {
                "name": "Teixeira de Mattos, Alexander",
                "birth_year": 1865,
                "death_year": 1921
            }
        ],
        "subjects": [
            "Homoptera",
            "Insects",
            "Orthoptera"
        ],
        "bookshelves": [],
        "languages": [
            "en"
        ],
        "copyright": false,
        "media_type": "Text",
        "formats": {
            "application/x-mobipocket-ebook": "https://www.gutenberg.org/ebooks/66650.kf8.images",
            "application/epub+zip": "https://www.gutenberg.org/ebooks/66650.epub3.images",
            "text/html": "https://www.gutenberg.org/ebooks/66650.html.images",
            "image/jpeg": "https://www.gutenberg.org/cache/epub/66650/pg66650.cover.medium.jpg",
            "application/octet-stream": "https://www.gutenberg.org/files/66650/66650-0.zip",
            "text/plain": "https://www.gutenberg.org/ebooks/66650.txt.utf-8",
            "application/rdf+xml": "https://www.gutenberg.org/ebooks/66650.rdf",
            "text/plain; charset=us-ascii": "https://www.gutenberg.org/files/66650/66650-0.txt"
        },
        "download_count": 60
    },
    {
        "id": 66870,
        "title": "Tibetan Tales, Derived from Indian Sources",
        "authors": [],
        "translators": [
            {
                "name": "Ralston, William Ralston Shedden",
                "birth_year": 1828,
                "death_year": 1889
            },
            {
                "name": "Schiefner, Anton",
                "birth_year": 1817,
                "death_year": 1879
            }
        ],
        "subjects": [
            "Buddhists -- China -- Tibet Autonomous Region -- Folklore",
            "Folklore -- China -- Tibet Autonomous Region",
            "Tales -- China -- Tibet Autonomous Region"
        ],
        "bookshelves": [],
        "languages": [
            "en"
        ],
        "copyright": false,
        "media_type": "Text",
        "formats": {
            "application/x-mobipocket-ebook": "https://www.gutenberg.org/ebooks/66870.kf8.images",
            "application/epub+zip": "https://www.gutenberg.org/ebooks/66870.epub3.images",
            "text/html": "https://www.gutenberg.org/ebooks/66870.html.images",
            "image/jpeg": "https://www.gutenberg.org/cache/epub/66870/pg66870.cover.medium.jpg",
            "application/octet-stream": "https://www.gutenberg.org/files/66870/66870-0.zip",
            "text/plain": "https://www.gutenberg.org/ebooks/66870.txt.utf-8",
            "application/rdf+xml": "https://www.gutenberg.org/ebooks/66870.rdf",
            "text/plain; charset=us-ascii": "https://www.gutenberg.org/files/66870/66870-0.txt"
        },
        "download_count": 60
    },
    {
        "id": 67535,
        "title": "Triste Fim de Polycarpo Quaresma",
        "authors": [
            {
                "name": "Barreto, Lima",
                "birth_year": 1881,
                "death_year": 1922
            }
        ],
        "translators": [],
        "subjects": [
            "Brazil -- Fiction",
            "Brazilian fiction"
        ],
        "bookshelves": [],
        "languages": [
            "pt"
        ],
        "copyright": false,
        "media_type": "Text",
        "formats": {
            "application/x-mobipocket-ebook": "https://www.gutenberg.org/ebooks/67535.kf8.images",
            "application/epub+zip": "https://www.gutenberg.org/ebooks/67535.epub3.images",
            "text/html": "https://www.gutenberg.org/ebooks/67535.html.images",
            "application/octet-stream": "https://www.gutenberg.org/files/67535/67535-0.zip",
            "image/jpeg": "https://www.gutenberg.org/cache/epub/67535/pg67535.cover.medium.jpg",
            "text/plain": "https://www.gutenberg.org/ebooks/67535.txt.utf-8",
            "application/rdf+xml": "https://www.gutenberg.org/ebooks/67535.rdf",
            "text/plain; charset=us-ascii": "https://www.gutenberg.org/files/67535/67535-0.txt"
        },
        "download_count": 60
    },
    {
        "id": 67938,
        "title": "Through Russian Central Asia",
        "authors": [
            {
                "name": "Graham, Stephen",
                "birth_year": 1884,
                "death_year": 1975
            }
        ],
        "translators": [],
        "subjects": [
            "Asia, Central -- Description and travel",
            "Graham, Stephen, 1884-1975 -- Travel -- Asia, Central"
        ],
        "bookshelves": [],
        "languages": [
            "en"
        ],
        "copyright": false,
        "media_type": "Text",
        "formats": {
            "application/x-mobipocket-ebook": "https://www.gutenberg.org/ebooks/67938.kf8.images",
            "application/epub+zip": "https://www.gutenberg.org/ebooks/67938.epub3.images",
            "text/html": "https://www.gutenberg.org/ebooks/67938.html.images",
            "application/octet-stream": "https://www.gutenberg.org/files/67938/67938-0.zip",
            "image/jpeg": "https://www.gutenberg.org/cache/epub/67938/pg67938.cover.medium.jpg",
            "text/plain": "https://www.gutenberg.org/ebooks/67938.txt.utf-8",
            "application/rdf+xml": "https://www.gutenberg.org/ebooks/67938.rdf",
            "text/plain; charset=us-ascii": "https://www.gutenberg.org/files/67938/67938-0.txt"
        },
        "download_count": 60
    },
    {
        "id": 67972,
        "title": "Moving Pictures: How They Are Made and Worked",
        "authors": [
            {
                "name": "Talbot, Frederick Arthur Ambrose",
                "birth_year": 1880,
                "death_year": 1924
            }
        ],
        "translators": [],
        "subjects": [
            "Motion pictures"
        ],
        "bookshelves": [],
        "languages": [
            "en"
        ],
        "copyright": false,
        "media_type": "Text",
        "formats": {
            "application/x-mobipocket-ebook": "https://www.gutenberg.org/ebooks/67972.kf8.images",
            "application/epub+zip": "https://www.gutenberg.org/ebooks/67972.epub3.images",
            "text/html": "https://www.gutenberg.org/ebooks/67972.html.images",
            "image/jpeg": "https://www.gutenberg.org/cache/epub/67972/pg67972.cover.medium.jpg",
            "application/octet-stream": "https://www.gutenberg.org/files/67972/67972-0.zip",
            "application/rdf+xml": "https://www.gutenberg.org/ebooks/67972.rdf",
            "text/plain": "https://www.gutenberg.org/ebooks/67972.txt.utf-8",
            "text/plain; charset=us-ascii": "https://www.gutenberg.org/files/67972/67972-0.txt"
        },
        "download_count": 60
    },
    {
        "id": 68243,
        "title": "The farmstead: The making of the rural home and the lay-out of the farm: (5th edition)",
        "authors": [
            {
                "name": "Roberts, Isaac Phillips",
                "birth_year": 1833,
                "death_year": 1928
            }
        ],
        "translators": [],
        "subjects": [
            "Farm buildings",
            "Farm life"
        ],
        "bookshelves": [],
        "languages": [
            "en"
        ],
        "copyright": false,
        "media_type": "Text",
        "formats": {
            "application/x-mobipocket-ebook": "https://www.gutenberg.org/ebooks/68243.kf8.images",
            "application/epub+zip": "https://www.gutenberg.org/ebooks/68243.epub3.images",
            "text/html": "https://www.gutenberg.org/ebooks/68243.html.images",
            "application/octet-stream": "https://www.gutenberg.org/files/68243/68243-0.zip",
            "text/plain": "https://www.gutenberg.org/ebooks/68243.txt.utf-8",
            "image/jpeg": "https://www.gutenberg.org/cache/epub/68243/pg68243.cover.medium.jpg",
            "application/rdf+xml": "https://www.gutenberg.org/ebooks/68243.rdf",
            "text/plain; charset=us-ascii": "https://www.gutenberg.org/files/68243/68243-0.txt"
        },
        "download_count": 60
    },
    {
        "id": 68326,
        "title": "History of electric light",
        "authors": [
            {
                "name": "Schroeder, Henry",
                "birth_year": 1879,
                "death_year": 1952
            }
        ],
        "translators": [],
        "subjects": [
            "Electric lighting -- History"
        ],
        "bookshelves": [],
        "languages": [
            "en"
        ],
        "copyright": false,
        "media_type": "Text",
        "formats": {
            "application/x-mobipocket-ebook": "https://www.gutenberg.org/ebooks/68326.kf8.images",
            "application/epub+zip": "https://www.gutenberg.org/ebooks/68326.epub3.images",
            "text/html": "https://www.gutenberg.org/ebooks/68326.html.images",
            "image/jpeg": "https://www.gutenberg.org/cache/epub/68326/pg68326.cover.medium.jpg",
            "application/octet-stream": "https://www.gutenberg.org/files/68326/68326-0.zip",
            "application/rdf+xml": "https://www.gutenberg.org/ebooks/68326.rdf",
            "text/plain": "https://www.gutenberg.org/ebooks/68326.txt.utf-8",
            "text/plain; charset=us-ascii": "https://www.gutenberg.org/files/68326/68326-0.txt"
        },
        "download_count": 60
    },
    {
        "id": 69646,
        "title": "Armenia, a martyr nation: A historical sketch of the Armenian people from traditional times to the present tragic days",
        "authors": [
            {
                "name": "Gabrielian, Mugurdich Chojhauji",
                "birth_year": 1857,
                "death_year": null
            }
        ],
        "translators": [],
        "subjects": [
            "Armenia",
            "Armenian question"
        ],
        "bookshelves": [],
        "languages": [
            "en"
        ],
        "copyright": false,
        "media_type": "Text",
        "formats": {
            "image/jpeg": "https://www.gutenberg.org/cache/epub/69646/pg69646.cover.medium.jpg",
            "application/rdf+xml": "https://www.gutenberg.org/ebooks/69646.rdf",
            "text/plain": "https://www.gutenberg.org/ebooks/69646.txt.utf-8",
            "application/x-mobipocket-ebook": "https://www.gutenberg.org/ebooks/69646.kf8.images",
            "application/epub+zip": "https://www.gutenberg.org/ebooks/69646.epub3.images",
            "text/html": "https://www.gutenberg.org/ebooks/69646.html.images",
            "application/octet-stream": "https://www.gutenberg.org/files/69646/69646-0.zip",
            "text/plain; charset=us-ascii": "https://www.gutenberg.org/files/69646/69646-0.txt"
        },
        "download_count": 60
    },
    {
        "id": 69650,
        "title": "Among Congo cannibals",
        "authors": [
            {
                "name": "Weeks, John H.",
                "birth_year": 1860,
                "death_year": 1924
            }
        ],
        "translators": [],
        "subjects": [
            "Congo (Democratic Republic)",
            "Ethnology -- Congo (Democratic Republic)",
            "Folklore -- Congo (Democratic Republic)"
        ],
        "bookshelves": [],
        "languages": [
            "en"
        ],
        "copyright": false,
        "media_type": "Text",
        "formats": {
            "image/jpeg": "https://www.gutenberg.org/cache/epub/69650/pg69650.cover.medium.jpg",
            "application/rdf+xml": "https://www.gutenberg.org/ebooks/69650.rdf",
            "text/plain": "https://www.gutenberg.org/ebooks/69650.txt.utf-8",
            "application/x-mobipocket-ebook": "https://www.gutenberg.org/ebooks/69650.kf8.images",
            "application/epub+zip": "https://www.gutenberg.org/ebooks/69650.epub3.images",
            "text/html": "https://www.gutenberg.org/ebooks/69650.html.images",
            "application/octet-stream": "https://www.gutenberg.org/files/69650/69650-0.zip",
            "text/plain; charset=us-ascii": "https://www.gutenberg.org/files/69650/69650-0.txt"
        },
        "download_count": 60
    },
    {
        "id": 69719,
        "title": "Galactic heritage",
        "authors": [
            {
                "name": "Long, Frank Belknap",
                "birth_year": 1903,
                "death_year": 1994
            }
        ],
        "translators": [],
        "subjects": [
            "Carnivals -- Fiction",
            "Inventions -- Fiction",
            "Psychic ability -- Fiction",
            "Science fiction",
            "Short stories"
        ],
        "bookshelves": [],
        "languages": [
            "en"
        ],
        "copyright": false,
        "media_type": "Text",
        "formats": {
            "image/jpeg": "https://www.gutenberg.org/cache/epub/69719/pg69719.cover.medium.jpg",
            "application/rdf+xml": "https://www.gutenberg.org/ebooks/69719.rdf",
            "text/plain": "https://www.gutenberg.org/ebooks/69719.txt.utf-8",
            "application/x-mobipocket-ebook": "https://www.gutenberg.org/ebooks/69719.kf8.images",
            "application/epub+zip": "https://www.gutenberg.org/ebooks/69719.epub3.images",
            "text/html": "https://www.gutenberg.org/ebooks/69719.html.images",
            "application/octet-stream": "https://www.gutenberg.org/files/69719/69719-0.zip",
            "text/plain; charset=us-ascii": "https://www.gutenberg.org/files/69719/69719-0.txt"
        },
        "download_count": 60
    },
    {
        "id": 69767,
        "title": "All about miniature plants and gardens indoors and out",
        "authors": [
            {
                "name": "Brilmayer, Bernice",
                "birth_year": null,
                "death_year": null
            }
        ],
        "translators": [],
        "subjects": [
            "Gardens, Miniature",
            "Miniature plants"
        ],
        "bookshelves": [],
        "languages": [
            "en"
        ],
        "copyright": false,
        "media_type": "Text",
        "formats": {
            "image/jpeg": "https://www.gutenberg.org/cache/epub/69767/pg69767.cover.medium.jpg",
            "application/rdf+xml": "https://www.gutenberg.org/ebooks/69767.rdf",
            "text/plain": "https://www.gutenberg.org/ebooks/69767.txt.utf-8",
            "application/x-mobipocket-ebook": "https://www.gutenberg.org/ebooks/69767.kf8.images",
            "application/epub+zip": "https://www.gutenberg.org/ebooks/69767.epub3.images",
            "text/html": "https://www.gutenberg.org/ebooks/69767.html.images",
            "application/octet-stream": "https://www.gutenberg.org/files/69767/69767-0.zip",
            "text/plain; charset=us-ascii": "https://www.gutenberg.org/files/69767/69767-0.txt"
        },
        "download_count": 60
    },
    {
        "id": 69818,
        "title": "An essay towards a natural history of serpents",
        "authors": [
            {
                "name": "Owen, Charles",
                "birth_year": null,
                "death_year": 1746
            }
        ],
        "translators": [],
        "subjects": [
            "Serpent worship -- Early works to 1800",
            "Serpents -- Early works to 1800",
            "Serpents -- Religious aspects -- Early works to 1800"
        ],
        "bookshelves": [],
        "languages": [
            "en"
        ],
        "copyright": false,
        "media_type": "Text",
        "formats": {
            "image/jpeg": "https://www.gutenberg.org/cache/epub/69818/pg69818.cover.medium.jpg",
            "application/rdf+xml": "https://www.gutenberg.org/ebooks/69818.rdf",
            "text/plain": "https://www.gutenberg.org/ebooks/69818.txt.utf-8",
            "application/x-mobipocket-ebook": "https://www.gutenberg.org/ebooks/69818.kf8.images",
            "application/epub+zip": "https://www.gutenberg.org/ebooks/69818.epub3.images",
            "text/html": "https://www.gutenberg.org/ebooks/69818.html.images",
            "application/octet-stream": "https://www.gutenberg.org/files/69818/69818-0.zip",
            "text/plain; charset=us-ascii": "https://www.gutenberg.org/files/69818/69818-0.txt"
        },
        "download_count": 60
    },
    {
        "id": 70193,
        "title": "With Washington in the west; $b or, A soldier boy's battles in the wilderness",
        "authors": [
            {
                "name": "Stratemeyer, Edward",
                "birth_year": 1862,
                "death_year": 1930
            }
        ],
        "translators": [],
        "subjects": [
            "Braddock, Edward, 1695?-1755 -- Juvenile fiction",
            "United States -- History -- French and Indian War, 1754-1763 -- Juvenile fiction",
            "War stories",
            "Washington, George, 1732-1799 -- Juvenile fiction"
        ],
        "bookshelves": [],
        "languages": [
            "en"
        ],
        "copyright": false,
        "media_type": "Text",
        "formats": {
            "image/jpeg": "https://www.gutenberg.org/cache/epub/70193/pg70193.cover.medium.jpg",
            "application/rdf+xml": "https://www.gutenberg.org/ebooks/70193.rdf",
            "text/plain": "https://www.gutenberg.org/ebooks/70193.txt.utf-8",
            "application/x-mobipocket-ebook": "https://www.gutenberg.org/ebooks/70193.kf8.images",
            "application/epub+zip": "https://www.gutenberg.org/ebooks/70193.epub3.images",
            "text/html": "https://www.gutenberg.org/ebooks/70193.html.images",
            "application/octet-stream": "https://www.gutenberg.org/files/70193/70193-0.zip",
            "text/plain; charset=us-ascii": "https://www.gutenberg.org/files/70193/70193-0.txt"
        },
        "download_count": 60
    },
    {
        "id": 70489,
        "title": "A true & exact history of the island of Barbados",
        "authors": [
            {
                "name": "Ligon, Richard",
                "birth_year": null,
                "death_year": 1662
            }
        ],
        "translators": [],
        "subjects": [
            "Barbados -- Description and travel",
            "Plants -- Barbados",
            "Sugar -- Manufacture and refining -- Barbados"
        ],
        "bookshelves": [],
        "languages": [
            "en"
        ],
        "copyright": false,
        "media_type": "Text",
        "formats": {
            "image/jpeg": "https://www.gutenberg.org/cache/epub/70489/pg70489.cover.medium.jpg",
            "application/rdf+xml": "https://www.gutenberg.org/ebooks/70489.rdf",
            "text/plain": "https://www.gutenberg.org/ebooks/70489.txt.utf-8",
            "application/x-mobipocket-ebook": "https://www.gutenberg.org/ebooks/70489.kf8.images",
            "application/epub+zip": "https://www.gutenberg.org/ebooks/70489.epub3.images",
            "text/html": "https://www.gutenberg.org/ebooks/70489.html.images",
            "application/octet-stream": "https://www.gutenberg.org/files/70489/70489-0.zip",
            "text/plain; charset=us-ascii": "https://www.gutenberg.org/files/70489/70489-0.txt"
        },
        "download_count": 60
    },
    {
        "id": 70537,
        "title": "The city of Jerusalem",
        "authors": [
            {
                "name": "Conder, C. R. (Claude Reignier)",
                "birth_year": 1848,
                "death_year": 1910
            }
        ],
        "translators": [],
        "subjects": [
            "Jerusalem -- Antiquities",
            "Jerusalem -- History"
        ],
        "bookshelves": [],
        "languages": [
            "en"
        ],
        "copyright": false,
        "media_type": "Text",
        "formats": {
            "image/jpeg": "https://www.gutenberg.org/cache/epub/70537/pg70537.cover.medium.jpg",
            "application/rdf+xml": "https://www.gutenberg.org/ebooks/70537.rdf",
            "text/plain": "https://www.gutenberg.org/ebooks/70537.txt.utf-8",
            "application/x-mobipocket-ebook": "https://www.gutenberg.org/ebooks/70537.kf8.images",
            "application/epub+zip": "https://www.gutenberg.org/ebooks/70537.epub3.images",
            "text/html": "https://www.gutenberg.org/ebooks/70537.html.images",
            "application/octet-stream": "https://www.gutenberg.org/files/70537/70537-0.zip",
            "text/plain; charset=us-ascii": "https://www.gutenberg.org/files/70537/70537-0.txt"
        },
        "download_count": 60
    },
    {
        "id": 70542,
        "title": "Comedias, tomo 3 de 3 : $b Las Fiestas de Ceres, las Ranas, las Junteras, Pluto",
        "authors": [
            {
                "name": "Aristophanes",
                "birth_year": -450,
                "death_year": -388
            }
        ],
        "translators": [
            {
                "name": "Bar\u00e1ibar y Zum\u00e1rraga, Federico",
                "birth_year": 1851,
                "death_year": 1918
            }
        ],
        "subjects": [
            "Aristophanes -- Translations into Spanish",
            "Athens (Greece) -- Drama",
            "Greek drama (Comedy) -- Translations into Spanish"
        ],
        "bookshelves": [],
        "languages": [
            "es"
        ],
        "copyright": false,
        "media_type": "Text",
        "formats": {
            "image/jpeg": "https://www.gutenberg.org/cache/epub/70542/pg70542.cover.medium.jpg",
            "application/rdf+xml": "https://www.gutenberg.org/ebooks/70542.rdf",
            "text/plain": "https://www.gutenberg.org/ebooks/70542.txt.utf-8",
            "application/x-mobipocket-ebook": "https://www.gutenberg.org/ebooks/70542.kf8.images",
            "application/epub+zip": "https://www.gutenberg.org/ebooks/70542.epub3.images",
            "text/html": "https://www.gutenberg.org/ebooks/70542.html.images",
            "application/octet-stream": "https://www.gutenberg.org/files/70542/70542-0.zip",
            "text/plain; charset=us-ascii": "https://www.gutenberg.org/files/70542/70542-0.txt"
        },
        "download_count": 60
    }
]